pbs_qhist-1.1.3.dist-info/licenses/LICENSE
qhist/__init__.py
qhist/qhist.py
qhist/cfg/default.json
qhist/cfg/example.json
qhist/extensions/ncar.py
qhist/test/test_outputs.py
qhist/test/test_time.py
qhist/test/testdata
pbs_qhist-1.1.3.dist-info/METADATA
pbs_qhist-1.1.3.dist-info/WHEEL
pbs_qhist-1.1.3.dist-info/entry_points.txt
pbs_qhist-1.1.3.dist-info/top_level.txt
pbs_qhist-1.1.3.dist-info/RECORD
