Metadata-Version: 2.4
Name: pbs-qhist
Version: 1.1.3
Summary: A utility to query historical PBS Pro job data
Author-email: Brian Vanderwende <vanderwb@ucar.edu>
License-Expression: MIT
Project-URL: homepage, https://github.com/NCAR/qhist
Project-URL: issues, https://github.com/NCAR/qhist/issues
Classifier: Programming Language :: Python :: 3
Classifier: Development Status :: 4 - Beta
Classifier: Operating System :: OS Independent
Classifier: Topic :: System :: Distributed Computing
Requires-Python: >=3.6
License-File: LICENSE
Requires-Dist: pbsparse>=0.2.4
Dynamic: license-file
